README.md
setup.py
cytimeutil/__init__.py
cytimeutil/cytimeutil.py
cytimeutil.egg-info/PKG-INFO
cytimeutil.egg-info/SOURCES.txt
cytimeutil.egg-info/dependency_links.txt
cytimeutil.egg-info/top_level.txt