Metadata-Version: 2.1
Name: cytimeutil
Version: 1.0.0
Summary: This is a Time calculation module
Home-page: https://upload.pypi.org/legacy
Author: lybule52
Author-email: ly352hz@163.com
License: UNKNOWN
Platform: UNKNOWN
Classifier: Programming Language :: Python :: 3
